viss/__init__.py
viss/__main__.py
viss-0.1.0.dist-info/LICENSE
viss-0.1.0.dist-info/METADATA
viss-0.1.0.dist-info/WHEEL
viss-0.1.0.dist-info/entry_points.txt
viss-0.1.0.dist-info/top_level.txt
viss-0.1.0.dist-info/RECORD
