Metadata-Version: 2.1
Name: viss
Version: 0.1.0
Summary: viss revolutionizes your workflow.
Author-email: David Bacelj <david.bacelj@gmail.com>
License: MIT License
Project-URL: Homepage, https://github.com/davidbacelj/test-project-1337-norditech
Keywords: testpackage,reader,tutorial
Classifier: Programming Language :: Python :: 3
Classifier: License :: OSI Approved :: MIT License
Classifier: Operating System :: OS Independent
Requires-Python: >=3.9
License-File: LICENSE
Requires-Dist: numpy
